fandabidozy/__init__.py
fandabidozy/mathops.py
fandabidozy-0.1.0.dist-info/METADATA
fandabidozy-0.1.0.dist-info/WHEEL
fandabidozy-0.1.0.dist-info/RECORD
